{
    "CUIL": "20219986751",
    "CuilFormateado": "20-21998675-1",
    "NroDocumento": "21998675",
    "Apellido": "Rodriguez",
    "Nombre": "Guillermo Horacio",
    "NombreFormateado": "Rodriguez, Guillermo Horacio",
    "FechaNacimiento": "10/09/1971",
    "Id_Sexo": "01",
    "PaiCodPais": "ARG",
    "Id_Numero": 0,
    "Id_Estado": 2,
    "Nivel1Seguro": "N",
    "Estado": "Verificado",
    "Email": "",
    "TelArea": "",
    "TelNro": "",
    "TelFormateado": "",
    "CelArea": "",
    "CelNro": "",
    "CelFormateado": "",
    "Empleado": "N",
    "Id_Empleado": "",
    "FechaRegistro": "26/11/2014 08:32:27",
    "FechaBloqueo": "",
    "IdAplicacionOrigen": "1",
    "Domicilio": {
        "IdVin": 0,
        "IdPais": null,
        "Pais": null,
        "IdProvincia": "",
        "Provincia": "",
        "IdDepartamento": 0,
        "Departamento": "",
        "IdLocalidad": 0,
        "Localidad": "",
        "IdBarrio": 0,
        "Barrio": "",
        "IdCalle": 0,
        "Calle": "",
        "Altura": "",
        "CodigoPostal": "",
        "Piso": "",
        "Depto": "",
        "Torre": "",
        "Manzana": null,
        "Lote": ""
    },
    "TieneRepresentados": "N",
    "CodigoIngresado": "N",
    "Constatado": "S",
    "Representado": {
        "RdoCuilCuit": "",
        "RdoNombre": "",
        "RdoDenominacion": "",
        "RdoTipo": "",
        "RdoIdEstado": null
    },
    "Respuesta": {
        "Resultado": "OK",
        "CodigoError": null,
        "SesionHash": "37666B4E6B354D36426B74484F503651324E71656731327A3857453D",
        "ExisteUsuario": null,
        "Servidor": "S2",
        "TimeStamp": "20220930123053597"
    },
    "Afip": {
        "Login": "N",
        "Fecha": ""
    },
    "RespuestaModificacion": {
        "IdAplicacion": 0,
        "FechaModificacion": ""
    }
}